waifuset/__init__.py
waifuset/const.py
waifuset/logging.py
waifuset/mapping.py
waifuset/tagging.py
waifuset/classes/__init__.py
waifuset/classes/data/__init__.py
waifuset/classes/data/data.py
waifuset/classes/data/data_utils.py
waifuset/classes/data/dict_data.py
waifuset/classes/data/eugedata.py
waifuset/classes/data/huggingface_data.py
waifuset/classes/data/image_info.py
waifuset/classes/data/caption/__init__.py
waifuset/classes/data/caption/caption.py
waifuset/classes/data/caption/table.py
waifuset/classes/database/__init__.py
waifuset/classes/database/sqlite3_database.py
waifuset/classes/dataset/__init__.py
waifuset/classes/dataset/auto_dataset.py
waifuset/classes/dataset/chain_dataset.py
waifuset/classes/dataset/chain_dataset_dev.py
waifuset/classes/dataset/csv_dataset.py
waifuset/classes/dataset/dataset.py
waifuset/classes/dataset/dataset_group.py
waifuset/classes/dataset/dataset_mixin.py
waifuset/classes/dataset/dict_dataset.py
waifuset/classes/dataset/directory_dataset.py
waifuset/classes/dataset/fast_dataset.py
waifuset/classes/dataset/hakubooru.py
waifuset/classes/dataset/huggingface_dataset.py
waifuset/classes/dataset/json_dataset.py
waifuset/classes/dataset/parasite_dataset.py
waifuset/classes/dataset/sqlite3_dataset.py
waifuset/classes/dataset/tools.py
waifuset/classes/dataset/t2i/__init__.py
waifuset/classes/dataset/t2i/arb.py
waifuset/classes/dataset/t2i/t2i_dataset.py
waifuset/components/__init__.py
waifuset/components/waifu_scorer/__init__.py
waifuset/components/waifu_scorer/mlp.py
waifuset/components/waifu_scorer/utils.py
waifuset/components/waifu_scorer/waifu_scorer.py
waifuset/components/waifu_tagger/__init__.py
waifuset/components/waifu_tagger/utils.py
waifuset/components/waifu_tagger/waifu_tagger.py
waifuset/components/waifu_upscaler/__init__.py
waifuset/components/waifu_upscaler/waifu_upscaler.py
waifuset/utils/__init__.py
waifuset/utils/class_utils.py
waifuset/utils/config_utils.py
waifuset/utils/file_utils.py
waifuset/utils/image_utils.py
waifuset-0.2.88.dist-info/LICENSE
waifuset-0.2.88.dist-info/METADATA
waifuset-0.2.88.dist-info/WHEEL
waifuset-0.2.88.dist-info/top_level.txt
waifuset-0.2.88.dist-info/RECORD
