Metadata-Version: 2.1
Name: waifuset
Version: 0.2.88
Summary: tools for text-to-image dataset
Home-page: https://github.com/Eugeoter/waifuset
Author: euge
Author-email: 1507064225@qq.com
License: UNKNOWN
Platform: UNKNOWN
Classifier: Development Status :: 3 - Alpha
Classifier: Intended Audience :: Developers
Classifier: License :: OSI Approved :: MIT License
Classifier: Programming Language :: Python :: 3
Classifier: Programming Language :: Python :: 3.8
License-File: LICENSE
Requires-Dist: pandas
Requires-Dist: tqdm
Requires-Dist: numpy
Requires-Dist: pillow
Requires-Dist: imagehash
Requires-Dist: datasets
Requires-Dist: opencv-python
Requires-Dist: absl-py
Requires-Dist: ml-collections
Requires-Dist: huggingface-hub
